mongocrud/__init__.py
mongocrud/mongomalbizer.py
mongo_malbizer-1.0.1.dist-info/METADATA
mongo_malbizer-1.0.1.dist-info/WHEEL
mongo_malbizer-1.0.1.dist-info/top_level.txt
mongo_malbizer-1.0.1.dist-info/RECORD
