Metadata-Version: 2.1
Name: mongo-malbizer
Version: 1.0.1
Summary: Python MongoDB CRUD
Home-page: UNKNOWN
Author: Anderson Souza
Author-email: anderson@malbizer.com.br
License: UNKNOWN
Keywords: python,mongobd,crud
Platform: UNKNOWN
Classifier: Development Status :: 2 - Pre-Alpha
Classifier: Programming Language :: Python :: 3
Classifier: Operating System :: MacOS :: MacOS X
Classifier: Operating System :: Microsoft :: Windows
Classifier: Operating System :: POSIX :: Linux
Requires-Dist: pymongo (==3.11.3)
